pyvenn/__init__.py
pyvenn/demo.py
pyvenn/venn.py
vcftoolz/__init__.py
vcftoolz/cli.py
vcftoolz/vcf_call_parser.py
vcftoolz/vcftoolz.py
vcftoolz-1.2.3.dist-info/AUTHORS.rst
vcftoolz-1.2.3.dist-info/LICENSE
vcftoolz-1.2.3.dist-info/METADATA
vcftoolz-1.2.3.dist-info/WHEEL
vcftoolz-1.2.3.dist-info/entry_points.txt
vcftoolz-1.2.3.dist-info/top_level.txt
vcftoolz-1.2.3.dist-info/RECORD
