Metadata-Version: 2.1
Name: vcftoolz
Version: 1.2.3
Summary: Tools for working with Variant Call Format files.
Home-page: https://github.com/CFSAN-Biostatistics/vcftoolz
Author: Steve Davis
Author-email: steven.davis@fda.hhs.gov
License: BSD
Keywords: bioinformatics,NGS,vcftoolz
Classifier: Development Status :: 5 - Production/Stable
Classifier: Intended Audience :: Developers
Classifier: Intended Audience :: Science/Research
Classifier: License :: Freely Distributable
Classifier: Natural Language :: English
Classifier: Programming Language :: Python :: 2
Classifier: Programming Language :: Python :: 2.7
Classifier: Programming Language :: Python :: 3
Classifier: Programming Language :: Python :: 3.3
Classifier: Programming Language :: Python :: 3.4
Classifier: Programming Language :: Python :: 3.5
Classifier: Programming Language :: Python :: 3.6
Classifier: Topic :: Scientific/Engineering :: Bio-Informatics
Requires-Python: >=3.9
License-File: LICENSE
License-File: AUTHORS.rst
Requires-Dist: biopython
Requires-Dist: numpy
Requires-Dist: pandas
Requires-Dist: PyVCF3
Requires-Dist: matplotlib
Requires-Dist: matplotlib-venn
